qr_console/__init__.py
qr_console/qr_console.py
qr_console-1.0.dist-info/LICENSE
qr_console-1.0.dist-info/METADATA
qr_console-1.0.dist-info/WHEEL
qr_console-1.0.dist-info/top_level.txt
qr_console-1.0.dist-info/RECORD
