Metadata-Version: 2.1
Name: qr-console
Version: 1.0
Summary: console app builder
Home-page: https://github.com/Kurush7/qr_console
Author: Kurush
Author-email: ze17@ya.ru
License: UNKNOWN
Platform: UNKNOWN
Classifier: Programming Language :: Python :: 3.6
Classifier: Operating System :: OS Independent
Requires-Python: >=3.6
License-File: LICENSE
Requires-Dist: argparse
Requires-Dist: colorama
